[{"model": "goods.categories", "pk": 1, "fields": {"name": "Все товары", "slug": "vse-tovary"}}, {"model": "goods.categories", "pk": 2, "fields": {"name": "Для лица", "slug": "dlya-lica"}}, {"model": "goods.categories", "pk": 3, "fields": {"name": "Для губ", "slug": "dlya-gub"}}, {"model": "goods.categories", "pk": 4, "fields": {"name": "Для глаз", "slug": "dlya-glaz"}}, {"model": "goods.categories", "pk": 5, "fields": {"name": "Для бровей", "slug": "dlya-brovej"}}, {"model": "goods.categories", "pk": 6, "fields": {"name": "Для ногтей", "slug": "dlya-nogtej"}}, {"model": "goods.categories", "pk": 7, "fields": {"name": "Уход за лицом", "slug": "uhod-za-licom"}}, {"model": "goods.categories", "pk": 8, "fields": {"name": "Уход за телом", "slug": "uhod-za-telom"}}, {"model": "goods.categories", "pk": 9, "fields": {"name": "Уход за волосами", "slug": "uhod-za-volosami"}}, {"model": "goods.categories", "pk": 10, "fields": {"name": "Аксессуары", "slug": "aksessuary"}}]